odoo10_addon_res_config_settings_enterprise_remove-10.0.1.0.0-py2.7-nspkg.pth
odoo/addons/res_config_settings_enterprise_remove/README.rst
odoo/addons/res_config_settings_enterprise_remove/__init__.py
odoo/addons/res_config_settings_enterprise_remove/__manifest__.py
odoo/addons/res_config_settings_enterprise_remove/models/__init__.py
odoo/addons/res_config_settings_enterprise_remove/models/res_config_settings.py
odoo/addons/res_config_settings_enterprise_remove/static/description/icon.png
odoo10_addon_res_config_settings_enterprise_remove-10.0.1.0.0.dist-info/DESCRIPTION.rst
odoo10_addon_res_config_settings_enterprise_remove-10.0.1.0.0.dist-info/METADATA
odoo10_addon_res_config_settings_enterprise_remove-10.0.1.0.0.dist-info/RECORD
odoo10_addon_res_config_settings_enterprise_remove-10.0.1.0.0.dist-info/WHEEL
odoo10_addon_res_config_settings_enterprise_remove-10.0.1.0.0.dist-info/metadata.json
odoo10_addon_res_config_settings_enterprise_remove-10.0.1.0.0.dist-info/namespace_packages.txt
odoo10_addon_res_config_settings_enterprise_remove-10.0.1.0.0.dist-info/top_level.txt
